regression_framework/__init__.py
regression_framework/bp/__init__.py
regression_framework/bp/regression_api.py
regression_framework/dmo/__init__.py
regression_framework/dmo/regression_execute_runner.py
regression_framework/dmo/regression_executor_comparator.py
regression_framework/router.py
regression_framework/svc/__init__.py
regression_framework/svc/filter_regression_tests.py
regression_framework/svc/load_regression_tests.py
regression_framework/svc/run_regression_tests.py
regression_framework-0.1.4.dist-info/WHEEL
regression_framework-0.1.4.dist-info/METADATA
regression_framework-0.1.4.dist-info/RECORD
