Metadata-Version: 2.1
Name: regression-framework
Version: 0.1.4
Summary: Provide a Framework for Regression Testing
Home-page: https://github.com/craigtrim/regression-framework
License: None
Keywords: testing,regression,agile,test-first,tdd
Author: Craig Trim
Author-email: craigtrim@gmail.com
Maintainer: Craig Trim
Maintainer-email: craigtrim@gmail.com
Requires-Python: >=3.8.5,<4.0.0
Classifier: Development Status :: 4 - Beta
Classifier: License :: Other/Proprietary License
Classifier: Programming Language :: Python :: 3
Classifier: Programming Language :: Python :: 3.10
Classifier: Programming Language :: Python :: 3.9
Classifier: Topic :: Software Development :: Libraries :: Python Modules
Requires-Dist: baseblock
Project-URL: Bug Tracker, https://github.com/craigtrim/regression-framework/issues
Project-URL: Repository, https://github.com/craigtrim/regression-framework
